v2.yaml
airflow_client/client/__init__.py
airflow_client/client/api_client.py
airflow_client/client/api_response.py
airflow_client/client/configuration.py
airflow_client/client/exceptions.py
airflow_client/client/py.typed
airflow_client/client/rest.py
airflow_client/client/api/__init__.py
airflow_client/client/api/asset_api.py
airflow_client/client/api/backfill_api.py
airflow_client/client/api/config_api.py
airflow_client/client/api/connection_api.py
airflow_client/client/api/dag_api.py
airflow_client/client/api/dag_parsing_api.py
airflow_client/client/api/dag_run_api.py
airflow_client/client/api/dag_source_api.py
airflow_client/client/api/dag_stats_api.py
airflow_client/client/api/dag_version_api.py
airflow_client/client/api/dag_warning_api.py
airflow_client/client/api/event_log_api.py
airflow_client/client/api/experimental_api.py
airflow_client/client/api/extra_links_api.py
airflow_client/client/api/import_error_api.py
airflow_client/client/api/job_api.py
airflow_client/client/api/login_api.py
airflow_client/client/api/monitor_api.py
airflow_client/client/api/plugin_api.py
airflow_client/client/api/pool_api.py
airflow_client/client/api/provider_api.py
airflow_client/client/api/task_api.py
airflow_client/client/api/task_instance_api.py
airflow_client/client/api/variable_api.py
airflow_client/client/api/version_api.py
airflow_client/client/api/x_com_api.py
airflow_client/client/models/__init__.py
airflow_client/client/models/app_builder_menu_item_response.py
airflow_client/client/models/app_builder_view_response.py
airflow_client/client/models/asset_alias_collection_response.py
airflow_client/client/models/asset_alias_response.py
airflow_client/client/models/asset_collection_response.py
airflow_client/client/models/asset_event_collection_response.py
airflow_client/client/models/asset_event_response.py
airflow_client/client/models/asset_response.py
airflow_client/client/models/backfill_collection_response.py
airflow_client/client/models/backfill_post_body.py
apache_airflow_client-3.1.6.dist-info/METADATA
apache_airflow_client-3.1.6.dist-info/WHEEL
apache_airflow_client-3.1.6.dist-info/licenses/LICENSE
apache_airflow_client-3.1.6.dist-info/licenses/NOTICE
apache_airflow_client-3.1.6.dist-info/RECORD
