Metadata-Version: 2.4
Name: apache-airflow-client
Version: 3.1.6
Summary: Apache Airflow API (Stable)
Project-URL: Bug Tracker, https://github.com/apache/airflow-client-python/issues
Project-URL: Changelog, https://github.com/apache/airflow-client-python/blob/main/CHANGELOG.md
Project-URL: Documentation, https://airflow.apache.org/docs/apache-airflow/stable/stable-rest-api-ref.html
Project-URL: Download, https://archive.apache.org/dist/airflow/clients/python/
Project-URL: Homepage, https://airflow.apache.org/
Project-URL: Source Code, https://github.com/apache/airflow/clients/python
Author-email: Apache Software Foundation <dev@airflow.apache.org>
License-Expression: Apache-2.0
License-File: LICENSE
License-File: NOTICE
Keywords: Apache Airflow API (Stable),OpenAPI,OpenAPI-Generator
Classifier: Development Status :: 5 - Production/Stable
Classifier: Environment :: Console
Classifier: Environment :: Web Environment
Classifier: Framework :: Apache Airflow
Classifier: Intended Audience :: Developers
Classifier: Intended Audience :: System Administrators
Classifier: Programming Language :: Python :: 3.10
Classifier: Programming Language :: Python :: 3.11
Classifier: Programming Language :: Python :: 3.12
Classifier: Topic :: System :: Monitoring
Requires-Python: >=3.10
Requires-Dist: pydantic>=2.11.0
Requires-Dist: python-dateutil
Requires-Dist: urllib3!=2.6.0,>=2.1.0
